fw_http_testserver.py
fw_http_testserver-1.2.3.dist-info/LICENSE
fw_http_testserver-1.2.3.dist-info/METADATA
fw_http_testserver-1.2.3.dist-info/WHEEL
fw_http_testserver-1.2.3.dist-info/RECORD
