Metadata-Version: 2.1
Name: fw-http-testserver
Version: 1.2.3
Summary: HTTP test server for mocking services
Home-page: https://gitlab.com/flywheel-io/tools/lib/fw-http-testserver
License: MIT
Keywords: Flywheel,HTTP,server,test,testing
Author: Flywheel
Author-email: support@flywheel.io
Requires-Python: >=3.9,<4.0
Classifier: License :: OSI Approved :: MIT License
Classifier: Programming Language :: Python :: 3
Classifier: Programming Language :: Python :: 3.9
Classifier: Programming Language :: Python :: 3.10
Classifier: Programming Language :: Python :: 3.11
Classifier: Programming Language :: Python :: 3.12
Classifier: Programming Language :: Python :: 3.13
Classifier: Topic :: Software Development :: Libraries :: Python Modules
Requires-Dist: flask (>=2.3.3)
Requires-Dist: fw-utils (>=3)
Requires-Dist: pytest (>=6)
Project-URL: Documentation, https://gitlab.com/flywheel-io/tools/lib/fw-http-testserver
Project-URL: Repository, https://gitlab.com/flywheel-io/tools/lib/fw-http-testserver
